<?xml version="1.0" encoding="UTF-8"?>
<Condition
    xmlns="http://hl7.org/fhir">
    <id value="SDOHCC-Condition-HungerVitalSign-Example-1"/>
    <meta>
        <versionId value="10"/>
        <lastUpdated value="2021-05-06T22:27:01.353+00:00"/>
        <source value="#VdaXb5kR9sZxJuW7"/>
    </meta>
    <clinicalStatus>
        <coding>
            <system value="http://terminology.hl7.org/CodeSystem/condition-clinical"/>
            <code value="active"/>
            <display value="Active"/>
        </coding>
    </clinicalStatus>
    <verificationStatus>
        <coding>
            <system value="http://terminology.hl7.org/CodeSystem/condition-ver-status"/>
            <code value="unconfirmed"/>
            <display value="Unconfirmed"/>
        </coding>
    </verificationStatus>
    <category>
        <coding>
            <system value="http://hl7.org/fhir/us/core/CodeSystem/condition-category"/>
            <code value="health-concern"/>
            <display value="Health Concern"/>
        </coding>
    </category>
    <category>
        <coding>
            <system value="http://hl7.org/fhir/us/sdoh-clinicalcare/CodeSystem/sdohcc-temporary-codes"/>
            <code value="food-insecurity"/>
            <display value="Food Insecurity"/>
        </coding>
    </category>
    <code>
        <coding>
            <system value="http://snomed.info/sct"/>
            <code value="733423003"/>
            <display value="Food insecurity"/>
        </coding>
    </code>
    <subject>
        <reference value="Patient/pat-53234"/>
        <display value="COLIN ABBAS"/>
    </subject>
    <onsetPeriod>
        <start value="2019-08-18T12:31:35.123Z"/>
    </onsetPeriod>
    <evidence>
        <detail>
            <reference value="Observation/SDOHCC-Observation-HungerVitalSign-Example-3"/>
        </detail>
    </evidence>
</Condition>